LICENSE
inbac/__init__.py
inbac/controller.py
inbac/inbac.py
inbac/model.py
inbac/parse_arguments.py
inbac/view.py
inbac-2.1.0.dist-info/entry_points.txt
inbac-2.1.0.dist-info/LICENSE
inbac-2.1.0.dist-info/WHEEL
inbac-2.1.0.dist-info/METADATA
inbac-2.1.0.dist-info/RECORD
