Metadata-Version: 2.1
Name: inbac
Version: 2.1.0
Summary: Interactive batch cropper made for quick cropping of images.
Home-page: https://github.com/weclaw1/inbac
License: MIT
Keywords: inbac,batch,image,crop
Author: Robert Węcławski
Author-email: r.weclawski@gmail.com
Requires-Python: >=3.6,<4.0
Classifier: Development Status :: 5 - Production/Stable
Classifier: Intended Audience :: Developers
Classifier: Intended Audience :: End Users/Desktop
Classifier: License :: OSI Approved :: MIT License
Classifier: Operating System :: OS Independent
Classifier: Programming Language :: Python :: 3
Classifier: Programming Language :: Python :: 3.6
Classifier: Programming Language :: Python :: 3.7
Classifier: Programming Language :: Python :: 3.8
Classifier: Programming Language :: Python :: 3.9
Classifier: Topic :: Multimedia :: Graphics :: Editors
Classifier: Topic :: Utilities
Requires-Dist: pillow (>=8.0,<9.0)
Project-URL: Repository, https://github.com/weclaw1/inbac
